{
  "slug": "to-ndc-or-not-ndc",
  "title": "To NDC or Not NDC - Is That the Question?",
  "excerpt": "After years of NDC discussions, the industry still needs 'demystifying' sessions. Perhaps we're asking the wrong questions entirely.",
  "author": "Ann Cederhall",
  "status": "published",
  "publishedAt": "2019-05-29",
  "updatedAt": "2019-05-29",
  "type": "LINKEDIN POST",
  "category": "Distribution",
  "readTimeMinutes": 5,
  "coverImage": null,
  "linkedinUrl": "https://www.linkedin.com/pulse/ndc-question-ann-cederhall",
  "content": "<p>Why, after 7 years, does the aviation industry still require 'demystifying NDC' conference sessions? The term itself is problematic—'New' oversells the concept, and industry stakeholders can't even agree on what it means.</p>\n\n<p>NDC is not a magic wand. It's only a very small part of the distribution puzzle. Your retail strategy is far more important—as is how you can improve the customer experience.</p>\n\n<p><a href=\"https://www.linkedin.com/pulse/ndc-question-ann-cederhall\" target=\"_blank\" rel=\"noopener noreferrer\" class=\"btn btn-primary\">Read the Full Article on LinkedIn →</a></p>"
}
